downd/__init__.py
downd/pyxdownload.py
pyxdownload-0.2.0.dist-info/METADATA
pyxdownload-0.2.0.dist-info/WHEEL
pyxdownload-0.2.0.dist-info/entry_points.txt
pyxdownload-0.2.0.dist-info/top_level.txt
pyxdownload-0.2.0.dist-info/RECORD
