Metadata-Version: 2.4
Name: pyxdownload
Version: 0.2.0
Author: luffpyx
Author-email: luffpyx@gmail.com
Dynamic: author
Dynamic: author-email
Dynamic: description
Dynamic: description-content-type
